LICENSE.txt
MANIFEST.in
README.rst
setup.cfg
setup.py
openet/__init__.py
openet/ndvi/__init__.py
openet/ndvi/collection.py
openet/ndvi/image.py
openet/ndvi/utils.py
openet/ndvi/tests/conftest.py
openet/ndvi/tests/test_collection.py
openet/ndvi/tests/test_image.py
openet/ndvi/tests/test_utils.py
openet_ndvi.egg-info/PKG-INFO
openet_ndvi.egg-info/SOURCES.txt
openet_ndvi.egg-info/dependency_links.txt
openet_ndvi.egg-info/not-zip-safe
openet_ndvi.egg-info/requires.txt
openet_ndvi.egg-info/top_level.txt