Metadata-Version: 1.1
Name: openet-ndvi
Version: 0.0.7
Summary: Earth Engine based NDVI ET Model
Home-page: https://github.com/Open-ET/openet-ndvi-beta
Author: Charles Morton
Author-email: charles.morton@dri.edu
License: Apache
Download-URL: https://github.com/Open-ET/openet-ndvi-beta/archive/v0.0.7.tar.gz
Keywords: NDVI OpenET Evapotranspiration Earth Engine
Platform: UNKNOWN
Classifier: License :: OSI Approved :: Apache Software License
Classifier: Programming Language :: Python :: 3.6
